README.rst
envparse.py
setup.py
envparse.egg-info/PKG-INFO
envparse.egg-info/SOURCES.txt
envparse.egg-info/dependency_links.txt
envparse.egg-info/not-zip-safe
envparse.egg-info/top_level.txt