Metadata-Version: 1.1
Name: envparse
Version: 0.1.6
Summary: Simple Environment Variable Parsing
Home-page: https://github.com/rconradharris/envparse
Author: Rick Harris
Author-email: rconradharris@gmail.com
License: MIT
Platform: any
Classifier: Environment :: Web Environment
Classifier: Intended Audience :: Developers
Classifier: License :: OSI Approved :: MIT License
Classifier: Operating System :: OS Independent
Classifier: Programming Language :: Python
Classifier: Topic :: Internet :: WWW/HTTP :: Dynamic Content
Classifier: Topic :: Software Development :: Libraries :: Python Modules
